classla/__init__.py
classla/_version.py
classla/models/__init__.py
classla/models/_training_logging.py
classla/models/charlm.py
classla/models/classifier.py
classla/models/identity_lemmatizer.py
classla/models/lemmatizer.py
classla/models/mwt_expander.py
classla/models/ner_tagger.py
classla/models/parser.py
classla/models/srl_tagger.py
classla/models/tagger.py
classla/models/classifiers/__init__.py
classla/models/classifiers/classifier_args.py
classla/models/classifiers/cnn_classifier.py
classla/models/classifiers/iterate_test.py
classla/models/common/__init__.py
classla/models/common/beam.py
classla/models/common/biaffine.py
classla/models/common/char_model.py
classla/models/common/chuliu_edmonds.py
classla/models/common/constant.py
classla/models/common/crf.py
classla/models/common/data.py
classla/models/common/doc.py
classla/models/common/dropout.py
classla/models/common/hlstm.py
classla/models/common/loss.py
classla/models/common/packed_lstm.py
classla/models/common/pretrain.py
classla/models/common/seq2seq_constant.py
classla/models/common/seq2seq_model.py
classla/models/common/seq2seq_modules.py
classla/models/common/seq2seq_utils.py
classla/models/common/trainer.py
classla/models/common/utils.py
classla/models/common/vocab.py
classla/models/depparse/__init__.py
classla/models/depparse/data.py
classla/models/depparse/model.py
classla/models/depparse/scorer.py
classla/models/depparse/trainer.py
classla/models/lemma/__init__.py
classla/models/lemma/data.py
classla/models/lemma/edit.py
classla/models/lemma/scorer.py
classla/models/lemma/trainer.py
classla/models/lemma/vocab.py
classla/models/mwt/__init__.py
classla/models/mwt/data.py
classla/models/mwt/scorer.py
classla/models/mwt/trainer.py
classla/models/mwt/vocab.py
classla/models/ner/__init__.py
classla/models/ner/data.py
classla/models/ner/model.py
classla/models/ner/scorer.py
classla/models/ner/trainer.py
classla/models/ner/utils.py
classla/models/ner/vocab.py
classla/models/pos/__init__.py
classla-2.1.1.dist-info/LICENSE
classla-2.1.1.dist-info/METADATA
classla-2.1.1.dist-info/WHEEL
classla-2.1.1.dist-info/top_level.txt
classla-2.1.1.dist-info/RECORD
