Metadata-Version: 2.1
Name: classla
Version: 2.1.1
Summary: Adapted Stanford NLP Python Library with improvements for specific languages.
Home-page: https://github.com/clarinsi/classla-stanfordnlp.git
Author: CLARIN.SI
Author-email: info@clarin.si
License: Apache License 2.0
Keywords: natural-language-processing nlp natural-language-understanding stanford-nlp deep-learning clarinsi
Classifier: Development Status :: 4 - Beta
Classifier: Intended Audience :: Developers
Classifier: Intended Audience :: Education
Classifier: Intended Audience :: Science/Research
Classifier: Intended Audience :: Information Technology
Classifier: Topic :: Scientific/Engineering
Classifier: Topic :: Scientific/Engineering :: Artificial Intelligence
Classifier: Topic :: Scientific/Engineering :: Information Analysis
Classifier: Topic :: Text Processing
Classifier: Topic :: Text Processing :: Linguistic
Classifier: Topic :: Software Development
Classifier: Topic :: Software Development :: Libraries
Classifier: Programming Language :: Python :: 3.6
Classifier: Programming Language :: Python :: 3.7
Classifier: Programming Language :: Python :: 3.8
Classifier: Programming Language :: Python :: 3.9
Classifier: Programming Language :: Python :: 3.10
Requires-Python: >=3.6
License-File: LICENSE
Requires-Dist: numpy ==1.23.0
Requires-Dist: protobuf ==4.21.2
Requires-Dist: requests ==2.28.0
Requires-Dist: torch ==1.12.0
Requires-Dist: tqdm ==4.62.3
Requires-Dist: obeliks ==1.1.6
Requires-Dist: reldi-tokeniser ==1.0.3
Provides-Extra: dev
Requires-Dist: check-manifest ; extra == 'dev'
Provides-Extra: test
Requires-Dist: coverage ; extra == 'test'
